AUTHORS
INSTALL
LICENSE
MANIFEST.in
README.rst
setup.cfg
setup.py
bin/git-crucible
crucible/__init__.py
crucible/__init__.pyc
crucible/client.py
crucible/client.pyc
crucible/commands.py
crucible/commands.pyc
crucible/git.py
crucible/git.pyc
crucible/rest.py
crucible/rest.pyc
crucible/tests/.test_git.py.swp
crucible/tests/__init__.py
crucible/tests/__init__.pyc
crucible/tests/test_api.py
crucible/tests/test_api.pyc
crucible/tests/test_git.py
crucible/tests/test_git.pyc
crucible/tests/test_rest.py
crucible/tests/test_rest.pyc
crucible/tests/data/add_patch_success_body.xml
crucible/tests/data/create_review_success_body.xml
crucible/tests/data/repo1/test1
crucible/tests/data/repo1/test2
crucible/tests/data/repo1/git/COMMIT_EDITMSG
crucible/tests/data/repo1/git/HEAD
crucible/tests/data/repo1/git/config
crucible/tests/data/repo1/git/description
crucible/tests/data/repo1/git/index
crucible/tests/data/repo1/git/hooks/applypatch-msg.sample
crucible/tests/data/repo1/git/hooks/commit-msg.sample
crucible/tests/data/repo1/git/hooks/post-commit.sample
crucible/tests/data/repo1/git/hooks/post-receive.sample
crucible/tests/data/repo1/git/hooks/post-update.sample
crucible/tests/data/repo1/git/hooks/pre-applypatch.sample
crucible/tests/data/repo1/git/hooks/pre-commit.sample
crucible/tests/data/repo1/git/hooks/pre-rebase.sample
crucible/tests/data/repo1/git/hooks/prepare-commit-msg.sample
crucible/tests/data/repo1/git/hooks/update.sample
crucible/tests/data/repo1/git/info/exclude
crucible/tests/data/repo1/git/logs/HEAD
crucible/tests/data/repo1/git/logs/refs/heads/master
crucible/tests/data/repo1/git/objects/18/0cf8328022becee9aaa2577a8f84ea2b9f3827
crucible/tests/data/repo1/git/objects/27/c61f03881ce7c516195d1c76f0af0a0c163d3a
crucible/tests/data/repo1/git/objects/42/9f51d815f06f9221ed886dc4967819ad1e6f0e
crucible/tests/data/repo1/git/objects/56/0ffc83faf16f018019e356b61bbfa137d62087
crucible/tests/data/repo1/git/objects/79/1190be8443f08e5e8d3abf53da7eeaec7690cd
git_crucible.egg-info/PKG-INFO
git_crucible.egg-info/SOURCES.txt
git_crucible.egg-info/dependency_links.txt
git_crucible.egg-info/requires.txt
git_crucible.egg-info/top_level.txt