Metadata-Version: 1.0
Name: git-crucible
Version: 0.1.2
Summary: Git extension that creates reviews in Crucible straight from the command line.
Home-page: http://github.com/rckclmbr/git-crucible
Author: Josh Braegger
Author-email: rckclmbr@gmail.com
License: BSD
Platform: UNKNOWN
Classifier: Programming Language :: Python
Classifier: Programming Language :: Python :: 2.6
Classifier: Programming Language :: Python :: 2.7
Classifier: License :: OSI Approved :: BSD License
Classifier: Operating System :: OS Independent
Classifier: Development Status :: 3 - Alpha
Classifier: Intended Audience :: Developers
Classifier: Environment :: Console
Classifier: Topic :: Software Development :: Libraries :: Application Frameworks
Classifier: Topic :: Software Development :: Libraries :: Python Modules
